AUTHORS.rst
CONTRIBUTING.rst
HISTORY.rst
LICENSE
MANIFEST.in
README.rst
setup.cfg
setup.py
docs/Makefile
docs/authors.rst
docs/conf.py
docs/contributing.rst
docs/history.rst
docs/index.rst
docs/installation.rst
docs/make.bat
docs/readme.rst
docs/usage.rst
pytextparser/__init__.py
pytextparser.egg-info/PKG-INFO
pytextparser.egg-info/SOURCES.txt
pytextparser.egg-info/dependency_links.txt
pytextparser.egg-info/not-zip-safe
pytextparser.egg-info/pbr.json
pytextparser.egg-info/top_level.txt
tests/__init__.py
tests/test_parser.py